<?xml version="1.0" encoding="UTF-8" standalone="yes"?>
<object-views xmlns="http://axelor.com/xml/ns/object-views"
  xmlns:xsi="http://www.w3.org/2001/XMLSchema-instance"
  xsi:schemaLocation="http://axelor.com/xml/ns/object-views http://axelor.com/xml/ns/object-views/object-views_7.4.xsd">

  <grid name="index-value-grid" title="Index values"
    model="com.axelor.apps.contract.db.IndexValue">
    <field name="startDate"/>
    <field name="endDate"/>
    <field name="value"/>
  </grid>

  <form name="index-value-form" title="Index value"
    model="com.axelor.apps.contract.db.IndexValue">
    <panel name="mainPanel">
      <field name="startDate"/>
      <field name="endDate"/>
      <field name="value"/>
    </panel>
  </form>
</object-views>