<?xml version="1.0" encoding="UTF-8" standalone="yes"?>
<object-views xmlns="http://axelor.com/xml/ns/object-views"
  xmlns:xsi="http://www.w3.org/2001/XMLSchema-instance"
  xsi:schemaLocation="http://axelor.com/xml/ns/object-views http://axelor.com/xml/ns/object-views/object-views_6.1.xsd">

  <grid name="journal-grid" title="Journal" model="com.axelor.apps.account.db.Journal">
    <toolbar>
      <button name="massUpdateBtn" title="Mass update status"
        onClick="action-mass-update-status-wizard"/>
    </toolbar>
    <field name="name"/>
    <field name="code" x-bind="{{code|unaccent|uppercase}}"/>
    <field name="journalType"/>
    <field name="exportCode"/>
    <field name="notExportOk"/>
    <field name="statusSelect"/>
    <field name="company" form-view="company-form" grid-view="company-grid"/>
  </grid>

  <form name="journal-form" title="Journal" model="com.axelor.apps.account.db.Journal"
    onNew="action-journal-group-on-new-actions" width="large"
    onLoad="action-journal-group-on-load-actions">
    <panel name="statusPanel" title="Status">
      <field name="statusSelect" showTitle="false" readonly="true" widget="NavSelect"
        colSpan="9"/>
      <button name="activeStatusBtn" title="Set Active"
        onClick="action-journal-group-on-click-active-status-actions" colSpan="2"/>
    </panel>
    <panel name="mainPanel">
      <field name="name" readonlyIf="$isReadOnly"/>
      <field name="code" x-bind="{{code|unaccent|uppercase}}" readonlyIf="$isReadOnly"/>
      <field name="company" canEdit="false"
        readonlyIf="statusSelect == 1 || statusSelect == 2 || $isReadOnly" form-view="company-form"
        grid-view="company-grid"
        onChange="action-journal-record-reset-valid-account-set,action-journal-record-change-config-values"/>
      <field name="journalType" grid-view="journal-type-grid" form-view="journal-type-form"/>
      <field name="authorizedFunctionalOriginSelect" widget="MultiSelect"/>
      <field name="journalType.isDisplayBalances" hidden="true"/>
      <field name="$isReadOnly" readonly="true" hidden="true"/>
    </panel>
    <panel name="totalPanel" showIf="id &amp;&amp; journalType.isDisplayBalances">
      <field name="$totalDebit" title="Total Debit" type="decimal" colSpan="4" readonly="true">
        <viewer>
					<![CDATA[
						<h3>{{$fmt('$totalDebit')}}</h3>
					]]>
        </viewer>
      </field>
      <field name="$totalCredit" title="Total Credit" type="decimal" colSpan="4"
        readonly="true">
        <viewer>
					<![CDATA[
						<h3>{{$fmt('$totalCredit')}}</h3>
					]]>
        </viewer>
      </field>
      <field name="$balance" title="Balance" type="decimal" colSpan="4" readonly="true">
        <viewer>
					<![CDATA[
						<h3>{{$fmt('$balance')}}</h3>
					]]>
        </viewer>
      </field>
    </panel>

    <panel-tabs name="mainPanelTab">

      <panel-dashlet name="viewMoveLinePanel" title="General"
        action="action-journal-view-move-line" height="450" canSearch="true" hideIf="$popup()"/>

      <panel name="configurationsPanel" title="Configurations" hideIf="$popup()">
        <panel name="moveLinePanel" title="MoveLine" colSpan="12">
          <field name="sequence" domain="self.codeSelect = 'move' and self.company = :company"
            form-view="sequence-form" grid-view="sequence-grid" canEdit="true" canNew="true"/>
          <field name="isInvoiceMoveConsolidated" widget="Boolean-switch"/>
          <field name="descriptionModel"/>
          <field name="descriptionIdentificationOk"/>
          <field name="authorizeSimulatedMove"
            showIf="company.accountConfig.isActivateSimulatedMove"/>
          <field name="allowAccountingDaybook"
            showIf="company.accountConfig.accountingDaybook"/>
          <panel name="originControlSettings" showTitle="false" colSpan="12">
            <field name="hasDuplicateDetectionOnOrigin"/>
            <field name="hasRequiredOrigin"/>
            <field name="prefixOrigin" requiredIf="hasDuplicateDetectionOnOrigin"/>
          </panel>
          <field name="company.accountConfig" hidden="true"/>
          <field name="company.accountConfig.isActivateSimulatedMove" hidden="true"/>
          <field name="company.accountConfig.accountingDaybook" hidden="true"/>
        </panel>
        <spacer name="moveLineSpacer"/>
        <panel name="paymentsPanel" title="Payments" colSpan="12">
          <field name="editReceiptOk" colSpan="6"/>
          <field name="excessPaymentOk" colSpan="6"/>
        </panel>
        <panel name="moveLinesSecuritySettingsPanel" title="Move lines security settings"
          colSpan="12">
          <field name="validAccountTypeSet" canNew="false" colSpan="6"
            form-view="account-type-form" grid-view="account-type-grid"/>
          <field name="validAccountSet" domain="self.company = :company" canNew="false"
            grid-view="account-simple-grid" colSpan="6" form-view="account-form"/>
        </panel>
        <spacer name="securitySettingsSpacer"/>
        <panel name="exportsPanel" title="Exports" colSpan="12">
          <field name="exportCode" readonlyIf="notExportOk"/>
          <field name="notExportOk" onChange="account-journal-on-change-not-export-ok"/>
        </panel>
        <field name="compatiblePartnerTypeSelect" widget="MultiSelect"/>
      </panel>

    </panel-tabs>



  </form>

  <action-view name="action-journal-view-move-line" title="Move lines"
    model="com.axelor.apps.account.db.MoveLine">
    <view type="grid" name="move-line-journal-grid"/>
    <view type="form" name="move-line-form"/>
    <domain>self.move.journal.id = :id and self.move.ignoreInAccountingOk IN ('false', null) and
      self.move.period.year.fromDate &lt; :todayDate and self.move.period.year.toDate &gt;
      :todayDate
    </domain>
    <context name="todayDate" expr="eval:__config__.date"/>
  </action-view>


  <action-record name="account-journal-record-default"
    model="com.axelor.apps.account.db.Journal">
    <field name="statusSelect" expr="eval: 0"/>
    <field name="company" expr="eval:__user__.activeCompany"
      if="__user__.activeCompany != null"/>
    <field name="company" expr="eval:__repo__(Company).all().fetchOne()"
      if="__user__.activeCompany == null &amp;&amp; __repo__(Company).all().count() == 1"/>
  </action-record>

  <action-method name="account-journal-method-status-active">
    <call class="com.axelor.apps.account.web.JournalController" method="toggleStatus"/>
  </action-method>

  <action-attrs name="action-attrs-account-journal-status-show-title">
    <attribute name="title" for="activeStatusBtn"
      expr="eval: com.axelor.i18n.I18n.get('Set Active')" if="statusSelect == 0"/>
    <attribute name="title" for="activeStatusBtn"
      expr="eval: com.axelor.i18n.I18n.get('Set Inactive')" if="statusSelect == 1"/>
  </action-attrs>

  <action-record name="account-journal-on-change-not-export-ok"
    model="com.axelor.apps.account.db.Journal">
    <field name="exportCode" expr="eval:null" if="notExportOk"/>
  </action-record>

  <action-record name="action-journal-record-reset-valid-account-set"
    model="com.axelor.apps.account.db.Journal">
    <field name="validAccountSet" expr="eval: null"/>
  </action-record>

  <action-group name="action-journal-group-on-load-actions">
    <action name="action-journal-method-set-totals" if="journalType.isDisplayBalances"/>
    <action name="action-method-account-journal-readonly-if-journal-in-move"/>
    <action name="action-attrs-account-journal-status-show-title"/>
    <action name="action-attrs-account-journal-readonly-if-account-in-move-line"/>
  </action-group>

  <action-group name="action-journal-group-on-new-actions">
    <action name="account-journal-record-default"/>
    <action name="action-method-account-journal-readonly-if-journal-in-move"/>
    <action name="action-attrs-account-journal-readonly-if-account-in-move-line"/>
  </action-group>

  <action-group name="action-journal-group-on-click-active-status-actions">
    <action name="save"/>
    <action name="account-journal-method-status-active"/>
    <action name="action-method-account-journal-readonly-if-journal-in-move"/>
    <action name="action-attrs-account-journal-status-show-title"/>
  </action-group>

  <action-method name="action-method-account-journal-readonly-if-journal-in-move">
    <call class="com.axelor.apps.account.web.JournalController" method="setReadOnly"/>
  </action-method>

  <action-method name="action-journal-method-set-totals">
    <call class="com.axelor.apps.account.web.JournalController" method="computeBalance"/>
  </action-method>

  <action-record name="action-journal-record-change-config-values"
    model="com.axelor.apps.account.db.Journal">
    <field name="authorizeSimulatedMove"
      expr="eval: company?.accountConfig?.isActivateSimulatedMove"/>
    <field name="allowAccountingDaybook"
      expr="eval: company?.accountConfig?.accountingDaybook"/>
  </action-record>

  <action-attrs name="action-attrs-account-journal-readonly-if-account-in-move-line">
    <attribute name="value" for="$isReadOnly"
      expr="eval: __repo__(MoveLine).all().filter('self.move.journal = ?', __this__).count() > 0"/>
  </action-attrs>

</object-views>
